verilog/master.v
//iverilog -o master_tb .\master_tb.v ..\src\*.v 
module master #(parameter NBITS = 8)( input wire clk,      
                input wire[NBITS-1:0] data,
                input wire rstn,               
                output reg sda,
                output reg scl);     

	wire[$clog2(NBITS*2+1):0] count;
	reg [NBITS-1:0] data_register;

	counter c1(clk, rstn, count);

	integer a = 0;

	always @(posedge clk) begin
		if (rstn == 1) begin
			scl <= 0; 
			sda <= 0;
		end else begin
			if (a == 0) begin 
				if (count/2 == 0) begin
					sda <= 1'b0;
					data_register <= data;
					$display("Start Patron 1");
				end else if (count/2 > 0) begin
					sda <= data_register[(count/2)-1];
					scl <= 1'b1;
					$display(count);
					$display(data_register[(count/2)-1]);
					$display("---");
				end
				a = 1;
			end else begin
				if (count/2 == 0) begin
					sda <= 1'b1;
					scl <= 1'b1;
				end
				if (count/2 > 0) begin
					scl <= 1'b0;
					sda <= sda;
				end
				if (count/2 > 1) begin
					sda <= 1'b0;
				end
				a = 0;
			end
		end
	end
endmodule  

module counter #(parameter NBITS = 16) (input clk,      
                input rstn,               
                output reg[$clog2(NBITS+1):0] out );     

    always @ (posedge clk) begin  
        if (rstn == 1)   
            out <= 0;  
        else if (out < NBITS+1)
            out <= out + 1;
        else
            out <= 0;
    end  
endmodule

synth/out/master_tb.v
module master_tb;
    parameter MESSAGE_LENGTH = 8;
    
    reg clk, reset;
    reg[MESSAGE_LENGTH-1:0] data;
    wire sda;
    wire scl;

    master j2c(clk, data, reset, sda, scl);

    initial begin     
        clk=0;
        forever #20 clk=~clk;
    end

    initial begin
        $dumpfile("out/master.vcd");
        $dumpvars(4, data, clk, sda, scl, reset, j2c.count, j2c.data_register);
        $display("start");
        reset = 0;
        #30     
        reset = 1;
        #30
        reset = 0;
        data=8'b01011111;
        #800
        data=8'b10010101;
        #800
        data=8'b11110000;
        #800;
        data=8'b00001111;
        #800
        reset = 0;
        #50     
        reset = 1;
        #50
        reset = 0;
        data=8'b01011111;
        #800
        data=8'b10010101;
        #800
        data=8'b11110000;
        #800;
        data=8'b00001111;
        #800
        reset = 0;
        #50     
        reset = 1;
        #50
        reset = 0;
        data=8'b01011111;
        #800
        data=8'b10010101;
        #800
        data=8'b11110000;
        #800;
        data=8'b00001111;
        #800
        $finish;
        $display("finish");
    end
    
endmodule

verilog/out/master.vcd
$date
	Mon Mar 11 14:19:46 2024
$end
$version
	Icarus Verilog
$end
$timescale
	1s
$end
$scope module master_tb $end
$var reg 8 ! data [7:0] $end
$upscope $end
$scope module master_tb $end
$var reg 1 " clk $end
$upscope $end
$scope module master_tb $end
$var wire 1 # sda $end
$upscope $end
$scope module master_tb $end
$var wire 1 $ scl $end
$upscope $end
$scope module master_tb $end
$var reg 1 % reset $end
$upscope $end
$scope module master_tb $end
$scope module j2c $end
$var wire 6 & count [5:0] $end
$upscope $end
$upscope $end
$scope module master_tb $end
$scope module j2c $end
$var reg 8 ' data_register [7:0] $end
$upscope $end
$upscope $end
$enddefinitions $end
#0
$dumpvars
bx '
bx &
0%
x$
x#
0"
bx !
$end
#20
b0 &
1"
#30
1%
#40
0"
#60
1$
1#
b1 &
1"
b1011111 !
0%
#80
0"
#100
b10 &
b1011111 '
0#
1"
#120
0"
#140
0$
b11 &
1"
#160
0"
#180
b100 &
1$
1#
1"
#200
0"
#220
0#
0$
b101 &
1"
#240
0"
#260
b110 &
1$
1#
1"
#280
0"
#300
0#
0$
b111 &
1"
#320
0"
#340
b1000 &
1$
1#
1"
#360
0"
#380
0#
0$
b1001 &
1"
#400
0"
#420
b1010 &
1$
1#
1"
#440
0"
#460
0#
0$
b1011 &
1"
#480
0"
#500
b1100 &
1$
1#
1"
#520
0"
#540
0#
0$
b1101 &
1"
#560
0"
#580
b1110 &
1$
1"
#600
0"
#620
0$
b1111 &
1"
#640
0"
#660
b10000 &
1$
1#
1"
#680
0"
#700
0#
0$
b10001 &
1"
#720
0"
#740
b0 &
1$
1"
#760
0"
#780
1#
b1 &
1"
#800
0"
#820
b10 &
0#
1"
#840
0"
#860
0$
b11 &
1"
b10010101 !
#880
0"
#900
b100 &
1$
1#
1"
#920
0"
#940
0#
0$
b101 &
1"
#960
0"
#980
b110 &
1$
1#
1"
#1000
0"
#1020
0#
0$
b111 &
1"
#1040
0"
#1060
b1000 &
1$
1#
1"
#1080
0"
#1100
0#
0$
b1001 &
1"
#1120
0"
#1140
b1010 &
1$
1#
1"
#1160
0"
#1180
0#
0$
b1011 &
1"
#1200
0"
#1220
b1100 &
1$
1#
1"
#1240
0"
#1260
0#
0$
b1101 &
1"
#1280
0"
#1300
b1110 &
1$
1"
#1320
0"
#1340
0$
b1111 &
1"
#1360
0"
#1380
b10000 &
1$
1#
1"
#1400
0"
#1420
0#
0$
b10001 &
1"
#1440
0"
#1460
b0 &
1$
1"
#1480
0"
#1500
1#
b1 &
1"
#1520
0"
#1540
b10 &
b10010101 '
0#
1"
#1560
0"
#1580
0$
b11 &
1"
#1600
0"
#1620
b100 &
1$
1#
1"
#1640
0"
#1660
0#
0$
b101 &
1"
b11110000 !
#1680
0"
#1700
b110 &
1$
1"
#1720
0"
#1740
0$
b111 &
1"
#1760
0"
#1780
b1000 &
1$
1#
1"
#1800
0"
#1820
0#
0$
b1001 &
1"
#1840
0"
#1860
b1010 &
1$
1"
#1880
0"
#1900
0$
b1011 &
1"
#1920
0"
#1940
b1100 &
1$
1#
1"
#1960
0"
#1980
0#
0$
b1101 &
1"
#2000
0"
#2020
b1110 &
1$
1"
#2040
0"
#2060
0$
b1111 &
1"
#2080
0"
#2100
b10000 &
1$
1"
#2120
0"
#2140
0$
b10001 &
1"
#2160
0"
#2180
b0 &
1$
1#
1"
#2200
0"
#2220
b1 &
1"
#2240
0"
#2260
b10 &
b11110000 '
0#
1"
#2280
0"
#2300
0$
b11 &
1"
#2320
0"
#2340
b100 &
1$
1"
#2360
0"
#2380
0$
b101 &
1"
#2400
0"
#2420
b110 &
1$
1"
#2440
0"
#2460
0$
b111 &
1"
b1111 !
#2480
0"
#2500
b1000 &
1$
1"
#2520
0"
#2540
0$
b1001 &
1"
#2560
0"
#2580
b1010 &
1$
1"
#2600
0"
#2620
0$
b1011 &
1"
#2640
0"
#2660
b1100 &
1$
1#
1"
#2680
0"
#2700
0#
0$
b1101 &
1"
#2720
0"
#2740
b1110 &
1$
1#
1"
#2760
0"
#2780
0#
0$
b1111 &
1"
#2800
0"
#2820
b10000 &
1$
1#
1"
#2840
0"
#2860
0#
0$
b10001 &
1"
#2880
0"
#2900
b0 &
1$
1#
1"
#2920
0"
#2940
b1 &
1"
#2960
0"
#2980
b10 &
b1111 '
0#
1"
#3000
0"
#3020
0$
b11 &
1"
#3040
0"
#3060
b100 &
1$
1#
1"
#3080
0"
#3100
0#
0$
b101 &
1"
#3120
0"
#3140
b110 &
1$
1#
1"
#3160
0"
#3180
0#
0$
b111 &
1"
#3200
0"
#3220
b1000 &
1$
1#
1"
#3240
0"
#3260
0#
0$
b1001 &
1"
#3280
0"
#3300
b1010 &
1$
1#
1"
#3310
1%
#3320
0"
#3340
b0 &
1"
#3360
0"
b1011111 !
0%
#3380
b1 &
1"
#3400
0"
#3420
b1011111 '
0#
b10 &
1"
#3440
0"
#3460
b11 &
0$
1"
#3480
0"
#3500
1$
1#
b100 &
1"
#3520
0"
#3540
b101 &
0#
0$
1"
#3560
0"
#3580
1$
1#
b110 &
1"
#3600
0"
#3620
b111 &
0#
0$
1"
#3640
0"
#3660
1$
1#
b1000 &
1"
#3680
0"
#3700
b1001 &
0#
0$
1"
#3720
0"
#3740
1$
1#
b1010 &
1"
#3760
0"
#3780
b1011 &
0#
0$
1"
#3800
0"
#3820
1$
1#
b1100 &
1"
#3840
0"
#3860
b1101 &
0#
0$
1"
#3880
0"
#3900
1$
b1110 &
1"
#3920
0"
#3940
b1111 &
0$
1"
#3960
0"
#3980
1$
1#
b10000 &
1"
#4000
0"
#4020
b10001 &
0#
0$
1"
#4040
0"
#4060
1$
b0 &
1"
#4080
0"
#4100
b1 &
1#
1"
#4120
0"
#4140
0#
b10 &
1"
#4160
0"
b10010101 !
#4180
b11 &
0$
1"
#4200
0"
#4220
1$
1#
b100 &
1"
#4240
0"
#4260
b101 &
0#
0$
1"
#4280
0"
#4300
1$
1#
b110 &
1"
#4320
0"
#4340
b111 &
0#
0$
1"
#4360
0"
#4380
1$
1#
b1000 &
1"
#4400
0"
#4420
b1001 &
0#
0$
1"
#4440
0"
#4460
1$
1#
b1010 &
1"
#4480
0"
#4500
b1011 &
0#
0$
1"
#4520
0"
#4540
1$
1#
b1100 &
1"
#4560
0"
#4580
b1101 &
0#
0$
1"
#4600
0"
#4620
1$
b1110 &
1"
#4640
0"
#4660
b1111 &
0$
1"
#4680
0"
#4700
1$
1#
b10000 &
1"
#4720
0"
#4740
b10001 &
0#
0$
1"
#4760
0"
#4780
1$
b0 &
1"
#4800
0"
#4820
b1 &
1#
1"
#4840
0"
#4860
b10010101 '
0#
b10 &
1"
#4880
0"
#4900
b11 &
0$
1"
#4920
0"
#4940
1$
1#
b100 &
1"
#4960
0"
b11110000 !
#4980
b101 &
0#
0$
1"
#5000
0"
#5020
1$
b110 &
1"
#5040
0"
#5060
b111 &
0$
1"
#5080
0"
#5100
1$
1#
b1000 &
1"
#5120
0"
#5140
b1001 &
0#
0$
1"
#5160
0"
#5180
1$
b1010 &
1"
#5200
0"
#5220
b1011 &
0$
1"
#5240
0"
#5260
1$
1#
b1100 &
1"
#5280
0"
#5300
b1101 &
0#
0$
1"
#5320
0"
#5340
1$
b1110 &
1"
#5360
0"
#5380
b1111 &
0$
1"
#5400
0"
#5420
1$
b10000 &
1"
#5440
0"
#5460
b10001 &
0$
1"
#5480
0"
#5500
1$
1#
b0 &
1"
#5520
0"
#5540
b1 &
1"
#5560
0"
#5580
b11110000 '
0#
b10 &
1"
#5600
0"
#5620
b11 &
0$
1"
#5640
0"
#5660
1$
b100 &
1"
#5680
0"
#5700
b101 &
0$
1"
#5720
0"
#5740
1$
b110 &
1"
#5760
0"
b1111 !
#5780
b111 &
0$
1"
#5800
0"
#5820
1$
b1000 &
1"
#5840
0"
#5860
b1001 &
0$
1"
#5880
0"
#5900
1$
b1010 &
1"
#5920
0"
#5940
b1011 &
0$
1"
#5960
0"
#5980
1$
1#
b1100 &
1"
#6000
0"
#6020
b1101 &
0#
0$
1"
#6040
0"
#6060
1$
1#
b1110 &
1"
#6080
0"
#6100
b1111 &
0#
0$
1"
#6120
0"
#6140
1$
1#
b10000 &
1"
#6160
0"
#6180
b10001 &
0#
0$
1"
#6200
0"
#6220
1$
1#
b0 &
1"
#6240
0"
#6260
b1 &
1"
#6280
0"
#6300
b1111 '
0#
b10 &
1"
#6320
0"
#6340
b11 &
0$
1"
#6360
0"
#6380
1$
1#
b100 &
1"
#6400
0"
#6420
b101 &
0#
0$
1"
#6440
0"
#6460
1$
1#
b110 &
1"
#6480
0"
#6500
b111 &
0#
0$
1"
#6520
0"
#6540
1$
1#
b1000 &
1"
#6560
0"
#6580
b1001 &
0#
0$
1"
#6600
0"
#6610
1%
#6620
1#
1$
b0 &
1"
#6640
0"
#6660
b1 &
1"
b1011111 !
0%
#6680
0"
#6700
b1011111 '
0#
b10 &
1"
#6720
0"
#6740
b11 &
0$
1"
#6760
0"
#6780
1$
1#
b100 &
1"
#6800
0"
#6820
b101 &
0#
0$
1"
#6840
0"
#6860
1$
1#
b110 &
1"
#6880
0"
#6900
b111 &
0#
0$
1"
#6920
0"
#6940
1$
1#
b1000 &
1"
#6960
0"
#6980
b1001 &
0#
0$
1"
#7000
0"
#7020
1$
1#
b1010 &
1"
#7040
0"
#7060
b1011 &
0#
0$
1"
#7080
0"
#7100
1$
1#
b1100 &
1"
#7120
0"
#7140
b1101 &
0#
0$
1"
#7160
0"
#7180
1$
b1110 &
1"
#7200
0"
#7220
b1111 &
0$
1"
#7240
0"
#7260
1$
1#
b10000 &
1"
#7280
0"
#7300
b10001 &
0#
0$
1"
#7320
0"
#7340
1$
b0 &
1"
#7360
0"
#7380
b1 &
1#
1"
#7400
0"
#7420
0#
b10 &
1"
#7440
0"
#7460
b11 &
0$
1"
b10010101 !
#7480
0"
#7500
1$
1#
b100 &
1"
#7520
0"
#7540
b101 &
0#
0$
1"
#7560
0"
#7580
1$
1#
b110 &
1"
#7600
0"
#7620
b111 &
0#
0$
1"
#7640
0"
#7660
1$
1#
b1000 &
1"
#7680
0"
#7700
b1001 &
0#
0$
1"
#7720
0"
#7740
1$
1#
b1010 &
1"
#7760
0"
#7780
b1011 &
0#
0$
1"
#7800
0"
#7820
1$
1#
b1100 &
1"
#7840
0"
#7860
b1101 &
0#
0$
1"
#7880
0"
#7900
1$
b1110 &
1"
#7920
0"
#7940
b1111 &
0$
1"
#7960
0"
#7980
1$
1#
b10000 &
1"
#8000
0"
#8020
b10001 &
0#
0$
1"
#8040
0"
#8060
1$
b0 &
1"
#8080
0"
#8100
b1 &
1#
1"
#8120
0"
#8140
b10010101 '
0#
b10 &
1"
#8160
0"
#8180
b11 &
0$
1"
#8200
0"
#8220
1$
1#
b100 &
1"
#8240
0"
#8260
b101 &
0#
0$
1"
b11110000 !
#8280
0"
#8300
1$
b110 &
1"
#8320
0"
#8340
b111 &
0$
1"
#8360
0"
#8380
1$
1#
b1000 &
1"
#8400
0"
#8420
b1001 &
0#
0$
1"
#8440
0"
#8460
1$
b1010 &
1"
#8480
0"
#8500
b1011 &
0$
1"
#8520
0"
#8540
1$
1#
b1100 &
1"
#8560
0"
#8580
b1101 &
0#
0$
1"
#8600
0"
#8620
1$
b1110 &
1"
#8640
0"
#8660
b1111 &
0$
1"
#8680
0"
#8700
1$
b10000 &
1"
#8720
0"
#8740
b10001 &
0$
1"
#8760
0"
#8780
1$
1#
b0 &
1"
#8800
0"
#8820
b1 &
1"
#8840
0"
#8860
b11110000 '
0#
b10 &
1"
#8880
0"
#8900
b11 &
0$
1"
#8920
0"
#8940
1$
b100 &
1"
#8960
0"
#8980
b101 &
0$
1"
#9000
0"
#9020
1$
b110 &
1"
#9040
0"
#9060
b111 &
0$
1"
b1111 !
#9080
0"
#9100
1$
b1000 &
1"
#9120
0"
#9140
b1001 &
0$
1"
#9160
0"
#9180
1$
b1010 &
1"
#9200
0"
#9220
b1011 &
0$
1"
#9240
0"
#9260
1$
1#
b1100 &
1"
#9280
0"
#9300
b1101 &
0#
0$
1"
#9320
0"
#9340
1$
1#
b1110 &
1"
#9360
0"
#9380
b1111 &
0#
0$
1"
#9400
0"
#9420
1$
1#
b10000 &
1"
#9440
0"
#9460
b10001 &
0#
0$
1"
#9480
0"
#9500
1$
1#
b0 &
1"
#9520
0"
#9540
b1 &
1"
#9560
0"
#9580
b1111 '
0#
b10 &
1"
#9600
0"
#9620
b11 &
0$
1"
#9640
0"
#9660
1$
1#
b100 &
1"
#9680
0"
#9700
b101 &
0#
0$
1"
#9720
0"
#9740
1$
1#
b110 &
1"
#9760
0"
#9780
b111 &
0#
0$
1"
#9800
0"
#9820
1$
1#
b1000 &
1"
#9840
0"
#9860
b1001 &
0#
0$
1"
