synth/cells.v
//  |---v---|---v---|---v---|---v---|---v---|---v---|---v---|---v---|---v---|---v---|
//-
//-     $_BUF (A, Y)
//-
//- A buffer. This cell type is always optimized away by the opt_clean pass.
//-
//- Truth table:    A | Y
//-                ---+---
//-                 0 | 0
//-                 1 | 1
//-
module BUF (A, Y);
input A;
output Y;
assign Y = A;
endmodule

//  |---v---|---v---|---v---|---v---|---v---|---v---|---v---|---v---|---v---|---v---|
//-
//-     $_NOT (A, Y)
//-
//- An inverter gate.
//-
//- Truth table:    A | Y
//-                ---+---
//-                 0 | 1
//-                 1 | 0
//-
module NOT (A, Y);
input A;
output Y;
assign Y = ~A;
endmodule

//  |---v---|---v---|---v---|---v---|---v---|---v---|---v---|---v---|---v---|---v---|
//-
//-     $_NAND (A, B, Y)
//-
//- A 2-input NAND gate.
//-
//- Truth table:    A B | Y
//-                -----+---
//-                 0 0 | 1
//-                 0 1 | 1
//-                 1 0 | 1
//-                 1 1 | 0
//-
module NAND (A, B, Y);
input A, B;
output Y;
assign Y = ~(A & B);
endmodule

//  |---v---|---v---|---v---|---v---|---v---|---v---|---v---|---v---|---v---|---v---|
//-
//-     $_NOR (A, B, Y)
//-
//- A 2-input NOR gate.
//-
//- Truth table:    A B | Y
//-                -----+---
//-                 0 0 | 1
//-                 0 1 | 0
//-                 1 0 | 0
//-                 1 1 | 0
//-
module NOR (A, B, Y);
input A, B;
output Y;
assign Y = ~(A | B);
endmodule


//  |---v---|---v---|---v---|---v---|---v---|---v---|---v---|---v---|---v---|---v---|
//-
//-     $_DFF_N (D, C, Q)
//-
//- A negative edge D-type flip-flop.
//-
//- Truth table:    D C | Q
//-                -----+---
//-                 d \ | d
//-                 - - | q
//-
module DFF_N (D, C, Q);
input D, C;
output reg Q;
always @(negedge C) begin
	Q <= D;
end
endmodule

//  |---v---|---v---|---v---|---v---|---v---|---v---|---v---|---v---|---v---|---v---|
//-
//-     $_DFF_P (D, C, Q)
//-
//- A positive edge D-type flip-flop.
//-
//- Truth table:    D C | Q
//-                -----+---
//-                 d / | d
//-                 - - | q
//-
module DFF_P (D, C, Q);
input D, C;
output reg Q;
always @(posedge C) begin
	Q <= D;
end
endmodule

//  |---v---|---v---|---v---|---v---|---v---|---v---|---v---|---v---|---v---|---v---|
//-
//-     $_DFF_NN0 (D, C, R, Q)
//-
//- A negative edge D-type flip-flop with negative polarity reset.
//-
//- Truth table:    D C R | Q
//-                -------+---
//-                 - - 0 | 0
//-                 d \ - | d
//-                 - - - | q
//-
module DFF_NN0 (D, C, R, Q);
input D, C, R;
output reg Q;
always @(negedge C or negedge R) begin
	if (R == 0)
		Q <= 0;
	else
		Q <= D;
end
endmodule

//  |---v---|---v---|---v---|---v---|---v---|---v---|---v---|---v---|---v---|---v---|
//-
//-     $_DFF_NN1 (D, C, R, Q)
//-
//- A negative edge D-type flip-flop with negative polarity set.
//-
//- Truth table:    D C R | Q
//-                -------+---
//-                 - - 0 | 1
//-                 d \ - | d
//-                 - - - | q
//-
module DFF_NN1 (D, C, R, Q);
input D, C, R;
output reg Q;
always @(negedge C or negedge R) begin
	if (R == 0)
		Q <= 1;
	else
		Q <= D;
end
endmodule

//  |---v---|---v---|---v---|---v---|---v---|---v---|---v---|---v---|---v---|---v---|
//-
//-     $_DFF_NP0 (D, C, R, Q)
//-
//- A negative edge D-type flip-flop with positive polarity reset.
//-
//- Truth table:    D C R | Q
//-                -------+---
//-                 - - 1 | 0
//-                 d \ - | d
//-                 - - - | q
//-
module DFF_NP0 (D, C, R, Q);
input D, C, R;
output reg Q;
always @(negedge C or posedge R) begin
	if (R == 1)
		Q <= 0;
	else
		Q <= D;
end
endmodule

//  |---v---|---v---|---v---|---v---|---v---|---v---|---v---|---v---|---v---|---v---|
//-
//-     $_DFF_NP1 (D, C, R, Q)
//-
//- A negative edge D-type flip-flop with positive polarity set.
//-
//- Truth table:    D C R | Q
//-                -------+---
//-                 - - 1 | 1
//-                 d \ - | d
//-                 - - - | q
//-
module DFF_NP1 (D, C, R, Q);
input D, C, R;
output reg Q;
always @(negedge C or posedge R) begin
	if (R == 1)
		Q <= 1;
	else
		Q <= D;
end
endmodule

//  |---v---|---v---|---v---|---v---|---v---|---v---|---v---|---v---|---v---|---v---|
//-
//-     $_DFF_PN0 (D, C, R, Q)
//-
//- A positive edge D-type flip-flop with negative polarity reset.
//-
//- Truth table:    D C R | Q
//-                -------+---
//-                 - - 0 | 0
//-                 d / - | d
//-                 - - - | q
//-
module DFF_PN0 (D, C, R, Q);
input D, C, R;
output reg Q;
always @(posedge C or negedge R) begin
	if (R == 0)
		Q <= 0;
	else
		Q <= D;
end
endmodule

//  |---v---|---v---|---v---|---v---|---v---|---v---|---v---|---v---|---v---|---v---|
//-
//-     $_DFF_PN1 (D, C, R, Q)
//-
//- A positive edge D-type flip-flop with negative polarity set.
//-
//- Truth table:    D C R | Q
//-                -------+---
//-                 - - 0 | 1
//-                 d / - | d
//-                 - - - | q
//-
module DFF_PN1 (D, C, R, Q);
input D, C, R;
output reg Q;
always @(posedge C or negedge R) begin
	if (R == 0)
		Q <= 1;
	else
		Q <= D;
end
endmodule

//  |---v---|---v---|---v---|---v---|---v---|---v---|---v---|---v---|---v---|---v---|
//-
//-     $_DFF_PP0 (D, C, R, Q)
//-
//- A positive edge D-type flip-flop with positive polarity reset.
//-
//- Truth table:    D C R | Q
//-                -------+---
//-                 - - 1 | 0
//-                 d / - | d
//-                 - - - | q
//-
module DFF_PP0 (D, C, R, Q);
input D, C, R;
output reg Q;
always @(posedge C or posedge R) begin
	if (R == 1)
		Q <= 0;
	else
		Q <= D;
end
endmodule

//  |---v---|---v---|---v---|---v---|---v---|---v---|---v---|---v---|---v---|---v---|
//-
//-     $_DFF_PP1 (D, C, R, Q)
//-
//- A positive edge D-type flip-flop with positive polarity set.
//-
//- Truth table:    D C R | Q
//-                -------+---
//-                 - - 1 | 1
//-                 d / - | d
//-                 - - - | q
//-
module DFF_PP1 (D, C, R, Q);
input D, C, R;
output reg Q;
always @(posedge C or posedge R) begin
	if (R == 1)
		Q <= 1;
	else
		Q <= D;
end
endmodule

synth/out/synth_j2c.v
/* Generated by Yosys 0.32+74 (git sha1 b739213d9, gcc 11.4.0-1ubuntu1~22.04 -fPIC -Os) */

(* dynports =  1  *)
(* hdlname = "\\counter" *)
(* src = "out/counter.v:1.1-13.10" *)
module counter(clk, rstn, out);
  wire _00_;
  wire _01_;
  wire _02_;
  wire _03_;
  wire _04_;
  wire _05_;
  wire _06_;
  wire _07_;
  wire _08_;
  wire _09_;
  wire _10_;
  wire _11_;
  wire _12_;
  wire _13_;
  wire _14_;
  wire _15_;
  wire _16_;
  wire _17_;
  (* src = "out/counter.v:1.55-1.58" *)
  input clk;
  wire clk;
  (* src = "out/counter.v:3.54-3.57" *)
  output [3:0] out;
  wire [3:0] out;
  (* src = "out/counter.v:2.23-2.27" *)
  input rstn;
  wire rstn;
  NOT _18_ (
    .A(out[2]),
    .Y(_04_)
  );
  NOT _19_ (
    .A(rstn),
    .Y(_05_)
  );
  NOT _20_ (
    .A(out[3]),
    .Y(_06_)
  );
  NOR _21_ (
    .A(rstn),
    .B(out[3]),
    .Y(_07_)
  );
  NAND _22_ (
    .A(_05_),
    .B(_06_),
    .Y(_08_)
  );
  NOR _23_ (
    .A(out[0]),
    .B(_08_),
    .Y(_00_)
  );
  NAND _24_ (
    .A(out[0]),
    .B(out[1]),
    .Y(_09_)
  );
  NOT _25_ (
    .A(_09_),
    .Y(_10_)
  );
  NOR _26_ (
    .A(out[0]),
    .B(out[1]),
    .Y(_11_)
  );
  NOT _27_ (
    .A(_11_),
    .Y(_12_)
  );
  NAND _28_ (
    .A(_09_),
    .B(_12_),
    .Y(_13_)
  );
  NOR _29_ (
    .A(_08_),
    .B(_13_),
    .Y(_01_)
  );
  NOR _30_ (
    .A(_04_),
    .B(_09_),
    .Y(_14_)
  );
  NAND _31_ (
    .A(out[2]),
    .B(_10_),
    .Y(_15_)
  );
  NAND _32_ (
    .A(_04_),
    .B(_09_),
    .Y(_16_)
  );
  NAND _33_ (
    .A(_07_),
    .B(_16_),
    .Y(_17_)
  );
  NOR _34_ (
    .A(_14_),
    .B(_17_),
    .Y(_02_)
  );
  NOR _35_ (
    .A(_08_),
    .B(_15_),
    .Y(_03_)
  );
  (* src = "out/counter.v:5.5-12.8" *)
  DFF_P _36_ (
    .C(clk),
    .D(_00_),
    .Q(out[0])
  );
  (* src = "out/counter.v:5.5-12.8" *)
  DFF_P _37_ (
    .C(clk),
    .D(_01_),
    .Q(out[1])
  );
  (* src = "out/counter.v:5.5-12.8" *)
  DFF_P _38_ (
    .C(clk),
    .D(_02_),
    .Q(out[2])
  );
  (* src = "out/counter.v:5.5-12.8" *)
  DFF_P _39_ (
    .C(clk),
    .D(_03_),
    .Q(out[3])
  );
endmodule

(* hdlname = "\\j2c" *)
(* dynports =  1  *)
(* top =  1  *)
(* src = "out/j2c.v:2.1-47.10" *)
module j2c(clk, data, rstn, sda, scl);
  wire _000_;
  wire _001_;
  wire _002_;
  wire _003_;
  wire _004_;
  wire _005_;
  wire _006_;
  wire _007_;
  wire _008_;
  wire _009_;
  wire _010_;
  wire _011_;
  wire _012_;
  wire _013_;
  wire _014_;
  wire _015_;
  wire _016_;
  wire _017_;
  wire _018_;
  wire _019_;
  wire _020_;
  wire _021_;
  wire _022_;
  wire _023_;
  wire _024_;
  wire _025_;
  wire _026_;
  wire _027_;
  wire _028_;
  wire _029_;
  wire _030_;
  wire _031_;
  wire _032_;
  wire _033_;
  wire _034_;
  wire _035_;
  wire _036_;
  wire _037_;
  wire _038_;
  wire _039_;
  wire _040_;
  wire _041_;
  wire _042_;
  wire _043_;
  wire _044_;
  wire _045_;
  wire _046_;
  wire _047_;
  wire _048_;
  wire _049_;
  wire _050_;
  wire _051_;
  wire _052_;
  wire _053_;
  wire _054_;
  wire _055_;
  wire _056_;
  wire _057_;
  wire _058_;
  wire _059_;
  wire _060_;
  wire _061_;
  wire _062_;
  wire _063_;
  wire _064_;
  wire _065_;
  wire _066_;
  wire _067_;
  wire _068_;
  wire _069_;
  wire _070_;
  wire _071_;
  wire _072_;
  wire _073_;
  wire _074_;
  wire _075_;
  wire _076_;
  wire _077_;
  wire _078_;
  wire _079_;
  wire _080_;
  wire _081_;
  wire _082_;
  wire _083_;
  wire _084_;
  wire _085_;
  wire _086_;
  wire _087_;
  wire _088_;
  (* src = "out/j2c.v:2.56-2.59" *)
  input clk;
  wire clk;
  (* src = "out/j2c.v:8.33-8.38" *)
  wire [3:0] count;
  (* src = "out/j2c.v:3.48-3.52" *)
  input [7:0] data;
  wire [7:0] data;
  (* src = "out/j2c.v:9.27-9.40" *)
  wire [7:0] data_register;
  (* src = "out/j2c.v:4.28-4.32" *)
  input rstn;
  wire rstn;
  (* src = "out/j2c.v:6.28-6.31" *)
  output scl;
  wire scl;
  (* src = "out/j2c.v:5.28-5.31" *)
  output sda;
  wire sda;
  NOT _089_ (
    .A(data_register[5]),
    .Y(_036_)
  );
  NOT _090_ (
    .A(rstn),
    .Y(_037_)
  );
  NOT _091_ (
    .A(count[3]),
    .Y(_038_)
  );
  NOT _092_ (
    .A(count[1]),
    .Y(_039_)
  );
  NOT _093_ (
    .A(count[0]),
    .Y(_040_)
  );
  NOT _094_ (
    .A(count[2]),
    .Y(_041_)
  );
  NOR _095_ (
    .A(count[1]),
    .B(count[0]),
    .Y(_042_)
  );
  NAND _096_ (
    .A(_039_),
    .B(_040_),
    .Y(_043_)
  );
  NOR _097_ (
    .A(count[3]),
    .B(count[2]),
    .Y(_044_)
  );
  NAND _098_ (
    .A(_038_),
    .B(_041_),
    .Y(_045_)
  );
  NOR _099_ (
    .A(_043_),
    .B(_045_),
    .Y(_046_)
  );
  NAND _100_ (
    .A(_042_),
    .B(_044_),
    .Y(_047_)
  );
  NOR _101_ (
    .A(rstn),
    .B(_047_),
    .Y(_048_)
  );
  NAND _102_ (
    .A(_037_),
    .B(_046_),
    .Y(_049_)
  );
  NAND _103_ (
    .A(data_register[0]),
    .B(_049_),
    .Y(_050_)
  );
  NAND _104_ (
    .A(data[0]),
    .B(_048_),
    .Y(_051_)
  );
  NAND _105_ (
    .A(_050_),
    .B(_051_),
    .Y(_000_)
  );
  NAND _106_ (
    .A(data_register[1]),
    .B(_049_),
    .Y(_052_)
  );
  NAND _107_ (
    .A(data[1]),
    .B(_048_),
    .Y(_053_)
  );
  NAND _108_ (
    .A(_052_),
    .B(_053_),
    .Y(_001_)
  );
  NAND _109_ (
    .A(data_register[2]),
    .B(_049_),
    .Y(_054_)
  );
  NAND _110_ (
    .A(data[2]),
    .B(_048_),
    .Y(_055_)
  );
  NAND _111_ (
    .A(_054_),
    .B(_055_),
    .Y(_002_)
  );
  NAND _112_ (
    .A(data_register[3]),
    .B(_049_),
    .Y(_056_)
  );
  NAND _113_ (
    .A(data[3]),
    .B(_048_),
    .Y(_057_)
  );
  NAND _114_ (
    .A(_056_),
    .B(_057_),
    .Y(_003_)
  );
  NAND _115_ (
    .A(data_register[4]),
    .B(_049_),
    .Y(_058_)
  );
  NAND _116_ (
    .A(data[4]),
    .B(_048_),
    .Y(_059_)
  );
  NAND _117_ (
    .A(_058_),
    .B(_059_),
    .Y(_004_)
  );
  NAND _118_ (
    .A(data_register[5]),
    .B(_049_),
    .Y(_060_)
  );
  NAND _119_ (
    .A(data[5]),
    .B(_048_),
    .Y(_061_)
  );
  NAND _120_ (
    .A(_060_),
    .B(_061_),
    .Y(_005_)
  );
  NAND _121_ (
    .A(data_register[6]),
    .B(_049_),
    .Y(_062_)
  );
  NAND _122_ (
    .A(data[6]),
    .B(_048_),
    .Y(_063_)
  );
  NAND _123_ (
    .A(_062_),
    .B(_063_),
    .Y(_006_)
  );
  NAND _124_ (
    .A(data_register[7]),
    .B(_049_),
    .Y(_064_)
  );
  NAND _125_ (
    .A(data[7]),
    .B(_048_),
    .Y(_065_)
  );
  NAND _126_ (
    .A(_064_),
    .B(_065_),
    .Y(_007_)
  );
  NAND _127_ (
    .A(_039_),
    .B(count[0]),
    .Y(_066_)
  );
  NOR _128_ (
    .A(_045_),
    .B(_066_),
    .Y(_067_)
  );
  NAND _129_ (
    .A(clk),
    .B(_047_),
    .Y(_068_)
  );
  NOT _130_ (
    .A(_068_),
    .Y(_069_)
  );
  NOR _131_ (
    .A(_067_),
    .B(_068_),
    .Y(_070_)
  );
  NAND _132_ (
    .A(sda),
    .B(_067_),
    .Y(_071_)
  );
  NOR _133_ (
    .A(clk),
    .B(_047_),
    .Y(_072_)
  );
  NOT _134_ (
    .A(_072_),
    .Y(_073_)
  );
  NAND _135_ (
    .A(_071_),
    .B(_073_),
    .Y(_074_)
  );
  NOR _136_ (
    .A(_070_),
    .B(_074_),
    .Y(_075_)
  );
  NOR _137_ (
    .A(rstn),
    .B(_075_),
    .Y(_008_)
  );
  NOR _138_ (
    .A(_069_),
    .B(_072_),
    .Y(_076_)
  );
  NOR _139_ (
    .A(rstn),
    .B(_076_),
    .Y(_009_)
  );
  NOR _140_ (
    .A(count[2]),
    .B(_043_),
    .Y(_077_)
  );
  NAND _141_ (
    .A(_041_),
    .B(_042_),
    .Y(_078_)
  );
  NOR _142_ (
    .A(_041_),
    .B(_042_),
    .Y(_079_)
  );
  NAND _143_ (
    .A(count[2]),
    .B(_043_),
    .Y(_080_)
  );
  NAND _144_ (
    .A(count[1]),
    .B(count[0]),
    .Y(_081_)
  );
  NOT _145_ (
    .A(_081_),
    .Y(_082_)
  );
  NOR _146_ (
    .A(_042_),
    .B(_082_),
    .Y(_083_)
  );
  NAND _147_ (
    .A(_043_),
    .B(_081_),
    .Y(_084_)
  );
  NAND _148_ (
    .A(data_register[3]),
    .B(_084_),
    .Y(_085_)
  );
  NAND _149_ (
    .A(data_register[1]),
    .B(_083_),
    .Y(_086_)
  );
  NAND _150_ (
    .A(_085_),
    .B(_086_),
    .Y(_087_)
  );
  NOR _151_ (
    .A(count[0]),
    .B(_087_),
    .Y(_088_)
  );
  NOR _152_ (
    .A(data_register[0]),
    .B(_066_),
    .Y(_012_)
  );
  NOR _153_ (
    .A(data_register[2]),
    .B(_081_),
    .Y(_013_)
  );
  NOR _154_ (
    .A(_012_),
    .B(_013_),
    .Y(_014_)
  );
  NOT _155_ (
    .A(_014_),
    .Y(_015_)
  );
  NOR _156_ (
    .A(_088_),
    .B(_015_),
    .Y(_016_)
  );
  NOR _157_ (
    .A(_079_),
    .B(_016_),
    .Y(_017_)
  );
  NOR _158_ (
    .A(count[3]),
    .B(_017_),
    .Y(_018_)
  );
  NOR _159_ (
    .A(_077_),
    .B(_018_),
    .Y(_019_)
  );
  NAND _160_ (
    .A(_078_),
    .B(_080_),
    .Y(_020_)
  );
  NAND _161_ (
    .A(data_register[7]),
    .B(_084_),
    .Y(_021_)
  );
  NOR _162_ (
    .A(_036_),
    .B(_084_),
    .Y(_022_)
  );
  NOR _163_ (
    .A(count[0]),
    .B(_022_),
    .Y(_023_)
  );
  NAND _164_ (
    .A(_021_),
    .B(_023_),
    .Y(_024_)
  );
  NOR _165_ (
    .A(data_register[6]),
    .B(_081_),
    .Y(_025_)
  );
  NOR _166_ (
    .A(data_register[4]),
    .B(_066_),
    .Y(_026_)
  );
  NOR _167_ (
    .A(_025_),
    .B(_026_),
    .Y(_027_)
  );
  NAND _168_ (
    .A(_024_),
    .B(_027_),
    .Y(_028_)
  );
  NAND _169_ (
    .A(_020_),
    .B(_028_),
    .Y(_029_)
  );
  NAND _170_ (
    .A(_047_),
    .B(_029_),
    .Y(_030_)
  );
  NOR _171_ (
    .A(_019_),
    .B(_030_),
    .Y(_031_)
  );
  NOR _172_ (
    .A(_072_),
    .B(_031_),
    .Y(_032_)
  );
  NOR _173_ (
    .A(rstn),
    .B(_032_),
    .Y(_010_)
  );
  NAND _174_ (
    .A(scl),
    .B(_046_),
    .Y(_033_)
  );
  NAND _175_ (
    .A(_068_),
    .B(_033_),
    .Y(_034_)
  );
  NOT _176_ (
    .A(_034_),
    .Y(_035_)
  );
  NOR _177_ (
    .A(rstn),
    .B(_035_),
    .Y(_011_)
  );
  (* src = "out/j2c.v:13.2-28.5" *)
  DFF_P _178_ (
    .C(clk),
    .D(_000_),
    .Q(data_register[0])
  );
  (* src = "out/j2c.v:13.2-28.5" *)
  DFF_P _179_ (
    .C(clk),
    .D(_001_),
    .Q(data_register[1])
  );
  (* src = "out/j2c.v:13.2-28.5" *)
  DFF_P _180_ (
    .C(clk),
    .D(_002_),
    .Q(data_register[2])
  );
  (* src = "out/j2c.v:13.2-28.5" *)
  DFF_P _181_ (
    .C(clk),
    .D(_003_),
    .Q(data_register[3])
  );
  (* src = "out/j2c.v:13.2-28.5" *)
  DFF_P _182_ (
    .C(clk),
    .D(_004_),
    .Q(data_register[4])
  );
  (* src = "out/j2c.v:13.2-28.5" *)
  DFF_P _183_ (
    .C(clk),
    .D(_005_),
    .Q(data_register[5])
  );
  (* src = "out/j2c.v:13.2-28.5" *)
  DFF_P _184_ (
    .C(clk),
    .D(_006_),
    .Q(data_register[6])
  );
  (* src = "out/j2c.v:13.2-28.5" *)
  DFF_P _185_ (
    .C(clk),
    .D(_007_),
    .Q(data_register[7])
  );
  (* src = "out/j2c.v:30.2-46.5" *)
  DFF_N _186_ (
    .C(clk),
    .D(_008_),
    .Q(sda)
  );
  (* src = "out/j2c.v:30.2-46.5" *)
  DFF_N _187_ (
    .C(clk),
    .D(_009_),
    .Q(scl)
  );
  (* src = "out/j2c.v:13.2-28.5" *)
  DFF_P _188_ (
    .C(clk),
    .D(_010_),
    .Q(sda)
  );
  (* src = "out/j2c.v:13.2-28.5" *)
  DFF_P _189_ (
    .C(clk),
    .D(_011_),
    .Q(scl)
  );
  (* module_not_derived = 32'd1 *)
  (* src = "out/j2c.v:11.10-11.30" *)
  counter c1 (
    .clk(clk),
    .out(count),
    .rstn(rstn)
  );
endmodule

synth/out/j2c_tb.v
module j2c_tb;
    parameter MESSAGE_LENGTH = 8;
    
    reg clk, reset;
    reg[MESSAGE_LENGTH-1:0] data;
    wire sda;
    wire scl;

    j2c j2c(clk, data, reset, sda, scl);

    initial begin     
        clk=0;
        forever #20 clk=~clk;
    end

    initial begin
        $dumpfile("out/j2c.vcd");
        $dumpvars(4, data, clk, sda, scl, reset, j2c.count, j2c.data_register);
        $display("start");
        reset = 0;
        #30     
        reset = 1;
        #30
        reset = 0;
        data=8'b01011111;
        #800
        data=8'b10010101;
        #800
        data=8'b11110000;
        #800;
        data=8'b00001111;
        #800
        reset = 0;
        #50     
        reset = 1;
        #50
        reset = 0;
        data=8'b01011111;
        #800
        data=8'b10010101;
        #800
        data=8'b11110000;
        #800;
        data=8'b00001111;
        #800
        reset = 0;
        #50     
        reset = 1;
        #50
        reset = 0;
        data=8'b01011111;
        #800
        data=8'b10010101;
        #800
        data=8'b11110000;
        #800;
        data=8'b00001111;
        #800
        $finish;
        $display("finish");
    end
    
endmodule

synth/out/j2c.vcd
$date
	Mon Mar 25 10:10:05 2024
$end
$version
	Icarus Verilog
$end
$timescale
	1s
$end
$scope module j2c_tb $end
$var reg 8 ! data [7:0] $end
$upscope $end
$scope module j2c_tb $end
$var reg 1 " clk $end
$upscope $end
$scope module j2c_tb $end
$var wire 1 # sda $end
$upscope $end
$scope module j2c_tb $end
$var wire 1 $ scl $end
$upscope $end
$scope module j2c_tb $end
$var reg 1 % reset $end
$upscope $end
$scope module j2c_tb $end
$scope module j2c $end
$var wire 4 & count [3:0] $end
$upscope $end
$upscope $end
$scope module j2c_tb $end
$scope module j2c $end
$var wire 8 ' data_register [7:0] $end
$upscope $end
$upscope $end
$enddefinitions $end
#0
$dumpvars
bx '
bx &
0%
x$
x#
0"
bx !
$end
#20
1"
#30
1%
#40
0"
#60
b0 &
0$
0#
1"
b1011111 !
0%
#80
0"
#100
b1011111 '
x#
b1 &
1"
#120
x$
0"
#140
b10 &
1"
#160
1#
0"
#180
b11 &
1"
#200
0"
#220
b100 &
1"
#240
0"
#260
b101 &
1"
#280
0"
#300
b110 &
1"
#320
0"
#340
x#
b111 &
1"
#360
0"
#380
b1000 &
1#
1"
#400
0"
#420
x#
b0 &
1"
#440
0$
0#
0"
#460
b1 &
x#
1"
#480
x$
0"
#500
b10 &
1"
#520
1#
0"
#540
b11 &
1"
#560
0"
#580
b100 &
1"
#600
0"
#620
b101 &
1"
#640
0"
#660
b110 &
1"
#680
0"
#700
b111 &
x#
1"
#720
0"
#740
1#
b1000 &
1"
#760
0"
#780
b0 &
x#
1"
#800
0#
0$
0"
#820
x#
b1 &
1"
#840
x$
0"
#860
b10 &
1"
b10010101 !
#880
1#
0"
#900
b11 &
1"
#920
0"
#940
b100 &
1"
#960
0"
#980
b101 &
1"
#1000
0"
#1020
b110 &
1"
#1040
0"
#1060
x#
b111 &
1"
#1080
0"
#1100
b1000 &
1#
1"
#1120
0"
#1140
x#
b0 &
1"
#1160
0$
0#
0"
#1180
b1 &
x#
b10010101 '
1"
#1200
x$
0"
#1220
b10 &
1"
#1240
1#
0"
#1260
b11 &
x#
1"
#1280
0"
#1300
1#
b100 &
1"
#1320
0"
#1340
b101 &
x#
1"
#1360
0"
#1380
1#
b110 &
1"
#1400
0"
#1420
b111 &
x#
1"
#1440
0"
#1460
b1000 &
1"
#1480
0"
#1500
b0 &
1#
1"
#1520
x#
0$
0"
#1540
b1 &
1"
#1560
x$
0"
#1580
b10 &
1"
#1600
1#
0"
#1620
x#
b11 &
1"
#1640
0"
#1660
b100 &
1#
1"
b11110000 !
#1680
0"
#1700
x#
b101 &
1"
#1720
0"
#1740
b110 &
1#
1"
#1760
0"
#1780
x#
b111 &
1"
#1800
0"
#1820
b1000 &
1"
#1840
0"
#1860
1#
b0 &
1"
#1880
0$
x#
0"
#1900
b1 &
b11110000 '
1"
#1920
x$
0"
#1940
b10 &
1"
#1960
0"
#1980
b11 &
1"
#2000
0"
#2020
b100 &
1"
#2040
0"
#2060
b101 &
1"
#2080
0"
#2100
1#
b110 &
1"
#2120
0"
#2140
b111 &
1"
#2160
0"
#2180
b1000 &
1"
#2200
0"
#2220
b0 &
1"
#2240
x#
0$
0"
#2260
b1 &
1"
#2280
x$
0"
#2300
b10 &
1"
#2320
0"
#2340
b11 &
1"
#2360
0"
#2380
b100 &
1"
#2400
0"
#2420
b101 &
1"
#2440
0"
#2460
b110 &
1#
1"
b1111 !
#2480
0"
#2500
b111 &
1"
#2520
0"
#2540
b1000 &
1"
#2560
0"
#2580
b0 &
1"
#2600
0$
x#
0"
#2620
b1 &
b1111 '
1"
#2640
x$
0"
#2660
b10 &
1"
#2680
1#
0"
#2700
b11 &
1"
#2720
0"
#2740
b100 &
1"
#2760
0"
#2780
b101 &
1"
#2800
0"
#2820
x#
b110 &
1"
#2840
0"
#2860
b111 &
1"
#2880
0"
#2900
b1000 &
1"
#2920
0"
#2940
b0 &
1"
#2960
0#
0$
0"
#2980
x#
b1 &
1"
#3000
x$
0"
#3020
b10 &
1"
#3040
1#
0"
#3060
b11 &
1"
#3080
0"
#3100
b100 &
1"
#3120
0"
#3140
b101 &
1"
#3160
0"
#3180
b110 &
x#
1"
#3200
0"
#3220
b111 &
1"
#3240
0"
#3260
b1000 &
1"
#3280
0"
#3300
b0 &
1"
#3310
1%
#3320
0$
0#
0"
#3340
1"
#3360
0"
b1011111 !
0%
#3380
b1011111 '
x#
b1 &
1"
#3400
x$
0"
#3420
b10 &
1"
#3440
1#
0"
#3460
b11 &
1"
#3480
0"
#3500
b100 &
1"
#3520
0"
#3540
b101 &
1"
#3560
0"
#3580
b110 &
1"
#3600
0"
#3620
x#
b111 &
1"
#3640
0"
#3660
b1000 &
1#
1"
#3680
0"
#3700
x#
b0 &
1"
#3720
0$
0#
0"
#3740
b1 &
x#
1"
#3760
x$
0"
#3780
b10 &
1"
#3800
1#
0"
#3820
b11 &
1"
#3840
0"
#3860
b100 &
1"
#3880
0"
#3900
b101 &
1"
#3920
0"
#3940
b110 &
1"
#3960
0"
#3980
b111 &
x#
1"
#4000
0"
#4020
1#
b1000 &
1"
#4040
0"
#4060
b0 &
x#
1"
#4080
0#
0$
0"
#4100
x#
b1 &
1"
#4120
x$
0"
#4140
b10 &
1"
#4160
1#
0"
b10010101 !
#4180
b11 &
1"
#4200
0"
#4220
b100 &
1"
#4240
0"
#4260
b101 &
1"
#4280
0"
#4300
b110 &
1"
#4320
0"
#4340
x#
b111 &
1"
#4360
0"
#4380
b1000 &
1#
1"
#4400
0"
#4420
x#
b0 &
1"
#4440
0$
0#
0"
#4460
b1 &
x#
b10010101 '
1"
#4480
x$
0"
#4500
b10 &
1"
#4520
1#
0"
#4540
b11 &
x#
1"
#4560
0"
#4580
1#
b100 &
1"
#4600
0"
#4620
b101 &
x#
1"
#4640
0"
#4660
1#
b110 &
1"
#4680
0"
#4700
b111 &
x#
1"
#4720
0"
#4740
b1000 &
1"
#4760
0"
#4780
b0 &
1#
1"
#4800
x#
0$
0"
#4820
b1 &
1"
#4840
x$
0"
#4860
b10 &
1"
#4880
1#
0"
#4900
x#
b11 &
1"
#4920
0"
#4940
b100 &
1#
1"
#4960
0"
b11110000 !
#4980
x#
b101 &
1"
#5000
0"
#5020
b110 &
1#
1"
#5040
0"
#5060
x#
b111 &
1"
#5080
0"
#5100
b1000 &
1"
#5120
0"
#5140
1#
b0 &
1"
#5160
0$
x#
0"
#5180
b1 &
b11110000 '
1"
#5200
x$
0"
#5220
b10 &
1"
#5240
0"
#5260
b11 &
1"
#5280
0"
#5300
b100 &
1"
#5320
0"
#5340
b101 &
1"
#5360
0"
#5380
1#
b110 &
1"
#5400
0"
#5420
b111 &
1"
#5440
0"
#5460
b1000 &
1"
#5480
0"
#5500
b0 &
1"
#5520
x#
0$
0"
#5540
b1 &
1"
#5560
x$
0"
#5580
b10 &
1"
#5600
0"
#5620
b11 &
1"
#5640
0"
#5660
b100 &
1"
#5680
0"
#5700
b101 &
1"
#5720
0"
#5740
b110 &
1#
1"
#5760
0"
b1111 !
#5780
b111 &
1"
#5800
0"
#5820
b1000 &
1"
#5840
0"
#5860
b0 &
1"
#5880
0$
x#
0"
#5900
b1 &
b1111 '
1"
#5920
x$
0"
#5940
b10 &
1"
#5960
1#
0"
#5980
b11 &
1"
#6000
0"
#6020
b100 &
1"
#6040
0"
#6060
b101 &
1"
#6080
0"
#6100
x#
b110 &
1"
#6120
0"
#6140
b111 &
1"
#6160
0"
#6180
b1000 &
1"
#6200
0"
#6220
b0 &
1"
#6240
0#
0$
0"
#6260
x#
b1 &
1"
#6280
x$
0"
#6300
b10 &
1"
#6320
1#
0"
#6340
b11 &
1"
#6360
0"
#6380
b100 &
1"
#6400
0"
#6420
b101 &
1"
#6440
0"
#6460
b110 &
x#
1"
#6480
0"
#6500
b111 &
1"
#6520
0"
#6540
b1000 &
1"
#6560
0"
#6580
b0 &
1"
#6600
0$
0#
0"
#6610
1%
#6620
1"
#6640
0"
#6660
1"
b1011111 !
0%
#6680
0"
#6700
b1 &
x#
b1011111 '
1"
#6720
x$
0"
#6740
b10 &
1"
#6760
1#
0"
#6780
b11 &
1"
#6800
0"
#6820
b100 &
1"
#6840
0"
#6860
b101 &
1"
#6880
0"
#6900
b110 &
1"
#6920
0"
#6940
b111 &
x#
1"
#6960
0"
#6980
1#
b1000 &
1"
#7000
0"
#7020
b0 &
x#
1"
#7040
0#
0$
0"
#7060
x#
b1 &
1"
#7080
x$
0"
#7100
b10 &
1"
#7120
1#
0"
#7140
b11 &
1"
#7160
0"
#7180
b100 &
1"
#7200
0"
#7220
b101 &
1"
#7240
0"
#7260
b110 &
1"
#7280
0"
#7300
x#
b111 &
1"
#7320
0"
