synth/out/master.v
//iverilog -o master_tb .\master_tb.v ..\src\*.v 
module master #(parameter NBITS = 8)( input wire clk,      
                input wire[NBITS-1:0] data,
                input wire rstn,               
                output reg sda,
                output reg scl);     

	wire[$clog2(NBITS):0] count;
	reg [NBITS-1:0] data_register;

	counter c1(clk, rstn, count);

	always @(posedge clk) begin
		if (rstn == 1) begin
			scl <= 0; 
			sda <= 0;
		end else begin 
			if (count == 0) begin
				sda <= ~clk;
				data_register <= data;
				/*$display("Start Patron 1");*/
			end else if (count > 0) begin
				sda <= data_register[count-1];
				scl <= clk;
				/*$display(data_register[count-1]);*/
			end
		end
	end

	always @(negedge clk) begin
		if (rstn == 1) begin
			scl <= 0; 
			sda <= 0;
		end else begin
			if (count == 0) begin
				sda <= ~clk;
				scl <= ~clk;
			end
			if (count > 0) begin
				scl <= clk;
			end
			if (count > 1) begin
				sda <= clk;
			end
		end
	end
endmodule  

module counter #(parameter NBITS = 8) (input clk,      
                input rstn,               
                output reg[$clog2(NBITS):0] out );     

    always @ (posedge clk) begin  
        if (rstn == 1)   
            out <= 0;  
        else if (out < NBITS)
            out <= out + 1;
        else
            out <= 0;
    end  
endmodule

synth/out/master_tb.v
module master_tb;
    parameter MESSAGE_LENGTH = 8;
    
    reg clk, reset;
    reg[MESSAGE_LENGTH-1:0] data;
    wire sda;
    wire scl;

    master i2c(clk, data, reset, sda, scl);

    initial begin     
        clk=0;
        forever #20 clk=~clk;
    end

    initial begin
        $dumpfile("out/master.vcd");
        $dumpvars(4, data, clk, sda, scl, reset, i2c.count, i2c.data_register);
        $display("start");
        reset = 0;
        #50     
        reset = 1;
        #50
        reset = 0;
        data=8'b01011111;
        #800
        data=8'b10010101;
        #800
        data=8'b11110000;
        #800;
        data=8'b00001111;
        #800
        $display("finish");
        $finish;
    end
    
endmodule

synth/out/master.vcd
$date
	Tue Mar  5 16:14:56 2024
$end
$version
	Icarus Verilog
$end
$timescale
	1s
$end
$scope module master_tb $end
$var reg 8 ! data [7:0] $end
$upscope $end
$scope module master_tb $end
$var reg 1 " clk $end
$upscope $end
$scope module master_tb $end
$var wire 1 # sda $end
$upscope $end
$scope module master_tb $end
$var wire 1 $ scl $end
$upscope $end
$scope module master_tb $end
$var reg 1 % reset $end
$upscope $end
$scope module master_tb $end
$scope module i2c $end
$var wire 4 & count [3:0] $end
$upscope $end
$upscope $end
$scope module master_tb $end
$scope module i2c $end
$var wire 8 ' data_register [7:0] $end
$upscope $end
$upscope $end
$enddefinitions $end
#0
$dumpvars
bx '
bx &
0%
x$
x#
0"
bx !
$end
#20
1"
#40
0"
#50
1%
#60
b0 &
1"
#80
0#
0$
0"
#100
1"
b1011111 !
0%
#120
0"
#140
b1 &
x#
b1011111 '
1"
#160
x$
0"
#180
b10 &
1"
#200
1#
0"
#220
b11 &
1"
#240
0"
#260
b100 &
1"
#280
0"
#300
b101 &
1"
#320
0"
#340
b110 &
1"
#360
0"
#380
b111 &
x#
1"
#400
0"
#420
1#
b1000 &
1"
#440
0"
#460
b0 &
x#
1"
#480
0#
0$
0"
#500
x#
b1 &
1"
#520
x$
0"
#540
b10 &
1"
#560
1#
0"
#580
b11 &
1"
#600
0"
#620
b100 &
1"
#640
0"
#660
b101 &
1"
#680
0"
#700
b110 &
1"
#720
0"
#740
x#
b111 &
1"
#760
0"
#780
b1000 &
1#
1"
#800
0"
#820
x#
b0 &
1"
#840
0$
0#
0"
#860
b1 &
x#
1"
#880
x$
0"
#900
b10 &
1"
b10010101 !
#920
1#
0"
#940
b11 &
1"
#960
0"
#980
b100 &
1"
#1000
0"
#1020
b101 &
1"
#1040
0"
#1060
b110 &
1"
#1080
0"
#1100
b111 &
x#
1"
#1120
0"
#1140
1#
b1000 &
1"
#1160
0"
#1180
b0 &
x#
1"
#1200
0#
0$
0"
#1220
b10010101 '
x#
b1 &
1"
#1240
x$
0"
#1260
b10 &
1"
#1280
1#
0"
#1300
x#
b11 &
1"
#1320
0"
#1340
b100 &
1#
1"
#1360
0"
#1380
x#
b101 &
1"
#1400
0"
#1420
b110 &
1#
1"
#1440
0"
#1460
x#
b111 &
1"
#1480
0"
#1500
b1000 &
1"
#1520
0"
#1540
1#
b0 &
1"
#1560
0$
x#
0"
#1580
b1 &
1"
#1600
x$
0"
#1620
b10 &
1"
#1640
1#
0"
#1660
b11 &
x#
1"
#1680
0"
#1700
1#
b100 &
1"
b11110000 !
#1720
0"
#1740
b101 &
x#
1"
#1760
0"
#1780
1#
b110 &
1"
#1800
0"
#1820
b111 &
x#
1"
#1840
0"
#1860
b1000 &
1"
#1880
0"
#1900
b0 &
1#
1"
#1920
x#
0$
0"
#1940
b11110000 '
b1 &
1"
#1960
x$
0"
#1980
b10 &
1"
#2000
0"
#2020
b11 &
1"
#2040
0"
#2060
b100 &
1"
#2080
0"
#2100
b101 &
1"
#2120
0"
#2140
b110 &
1#
1"
#2160
0"
#2180
b111 &
1"
#2200
0"
#2220
b1000 &
1"
#2240
0"
#2260
b0 &
1"
#2280
0$
x#
0"
#2300
b1 &
1"
#2320
x$
0"
#2340
b10 &
1"
#2360
0"
#2380
b11 &
1"
#2400
0"
#2420
b100 &
1"
#2440
0"
#2460
b101 &
1"
#2480
0"
#2500
1#
b110 &
1"
b1111 !
#2520
0"
#2540
b111 &
1"
#2560
0"
#2580
b1000 &
1"
#2600
0"
#2620
b0 &
1"
#2640
x#
0$
0"
#2660
b1111 '
b1 &
1"
#2680
x$
0"
#2700
b10 &
1"
#2720
1#
0"
#2740
b11 &
1"
#2760
0"
#2780
b100 &
1"
#2800
0"
#2820
b101 &
1"
#2840
0"
#2860
b110 &
x#
1"
#2880
0"
#2900
b111 &
1"
#2920
0"
#2940
b1000 &
1"
#2960
0"
#2980
b0 &
1"
#3000
0$
0#
0"
#3020
b1 &
x#
1"
#3040
x$
0"
#3060
b10 &
1"
#3080
1#
0"
#3100
b11 &
1"
#3120
0"
#3140
b100 &
1"
#3160
0"
#3180
b101 &
1"
#3200
0"
#3220
x#
b110 &
1"
#3240
0"
#3260
b111 &
1"
#3280
0"
#3300
b1000 &
1"
