synth/out/master.v
//iverilog -o master_tb .\master_tb.v ..\src\*.v 
module master #(parameter MESSAGE_LENGTH = 8)( input wire clk,      
                input wire[MESSAGE_LENGTH-1:0] data,
                input wire rst,               
                output reg sda,
                output reg scl);     

	wire[$clog2(MESSAGE_LENGTH*2+1):0] count;
	reg [MESSAGE_LENGTH-1:0] data_register;

	counter c1(clk, rst, count);

	integer a = 0;

	always @(posedge clk) begin
		if (rst == 1) begin
			scl <= 1; 
			sda <= 1;
		end else begin
			if (a == 0) begin 
				if (count/2 == 0) begin
					sda <= 1'b0;
					data_register <= data;
					$display("Start Patron 1");
				end else if (count/2 > 0) begin
					sda <= data_register[(count/2)-1];
					scl <= 1'b1;
					$display(count);
					$display(data_register[(count/2)-1]);
					$display("---");
				end
				a = 1;
			end else begin
				if (count/2 == 0) begin
					sda <= 1'b1;
					scl <= 1'b1;
				end
				if (count/2 > 0) begin
					scl <= 1'b0;
					sda <= sda;
				end
				if (count/2 > 1) begin
					sda <= 1'b0;
				end
				a = 0;
			end
		end
	end
endmodule  

module counter #(parameter MESSAGE_LENGTH = 8) (input clk,      
                input rst,               
                output reg[$clog2(MESSAGE_LENGTH*2+1):0] out );     

    always @ (posedge clk) begin  
        if (rst == 1)   
            out <= 0;  
        else if (out < MESSAGE_LENGTH*2+1)
            out <= out + 1;
        else
            out <= 0;
    end  
endmodule

synth/out/master_tb.v
module master_tb;
    parameter MESSAGE_LENGTH = 8;
    
    reg clk, reset;
    reg[MESSAGE_LENGTH-1:0] data;
    wire sda;
    wire scl;

    master j2c(clk, data, reset, sda, scl);

    initial begin     
        clk=0;
        forever #20 clk=~clk;
    end

    initial begin
        $dumpfile("out/master.vcd");
        $dumpvars(4, data, clk, sda, scl, reset, j2c.count, j2c.data_register);
        $display("start");
        reset = 0;
        #50     
        reset = 1;
        #50
        reset = 0;
        data=8'b01011111;
        #800
        data=8'b10010101;
        #800
        data=8'b11110000;
        #800;
        data=8'b00001111;
        #800
        $display("finish");
        $finish;
    end
    
endmodule

synth/out/master.vcd
$date
	Mon Mar 11 13:10:48 2024
$end
$version
	Icarus Verilog
$end
$timescale
	1s
$end
$scope module master_tb $end
$var reg 8 ! data [7:0] $end
$upscope $end
$scope module master_tb $end
$var reg 1 " clk $end
$upscope $end
$scope module master_tb $end
$var wire 1 # sda $end
$upscope $end
$scope module master_tb $end
$var wire 1 $ scl $end
$upscope $end
$scope module master_tb $end
$var reg 1 % reset $end
$upscope $end
$scope module master_tb $end
$scope module j2c $end
$var wire 6 & count [5:0] $end
$upscope $end
$upscope $end
$scope module master_tb $end
$scope module j2c $end
$var wire 8 ' data_register [7:0] $end
$upscope $end
$upscope $end
$enddefinitions $end
#0
$dumpvars
bx '
bx &
0%
x$
x#
0"
bx !
$end
#20
b0xxxxx &
1"
#40
0"
#50
1%
#60
b0 &
1$
1#
1"
#80
0"
#100
1"
b1011111 !
0%
#120
0"
#140
b1 &
x#
1"
#160
0"
#180
b10 &
1"
#200
0"
#220
b11 &
x$
1"
#240
0"
#260
b100 &
1"
#280
0"
#300
b101 &
1"
#320
0"
#340
b110 &
1"
#360
0"
#380
b111 &
1"
#400
0"
#420
b1000 &
1"
#440
0"
#460
b1001 &
1"
#480
0"
#500
b1010 &
1"
#520
0"
#540
b1011 &
1"
#560
0"
#580
b1100 &
1"
#600
0"
#620
b1101 &
1"
#640
0"
#660
b1110 &
1"
#680
0"
#700
b1111 &
1"
#720
0"
#740
b10000 &
1"
#760
0"
#780
b10001 &
1"
#800
0"
#820
b0 &
1"
#840
0"
#860
b1 &
1"
#880
0"
#900
b10 &
1"
b10010101 !
#920
0"
#940
b11 &
1"
#960
0"
#980
b100 &
1"
#1000
0"
#1020
b101 &
1"
#1040
0"
#1060
b110 &
1"
#1080
0"
#1100
b111 &
1"
#1120
0"
#1140
b1000 &
1"
#1160
0"
#1180
b1001 &
1"
#1200
0"
#1220
b1010 &
1"
#1240
0"
#1260
b1011 &
1"
#1280
0"
#1300
b1100 &
1"
#1320
0"
#1340
b1101 &
1"
#1360
0"
#1380
b1110 &
1"
#1400
0"
#1420
b1111 &
1"
#1440
0"
#1460
b10000 &
1"
#1480
0"
#1500
b10001 &
1"
#1520
0"
#1540
b0 &
1"
#1560
0"
#1580
b1 &
1"
#1600
0"
#1620
b10 &
1"
#1640
0"
#1660
b11 &
1"
#1680
0"
#1700
b100 &
1"
b11110000 !
#1720
0"
#1740
b101 &
1"
#1760
0"
#1780
b110 &
1"
#1800
0"
#1820
b111 &
1"
#1840
0"
#1860
b1000 &
1"
#1880
0"
#1900
b1001 &
1"
#1920
0"
#1940
b1010 &
1"
#1960
0"
#1980
b1011 &
1"
#2000
0"
#2020
b1100 &
1"
#2040
0"
#2060
b1101 &
1"
#2080
0"
#2100
b1110 &
1"
#2120
0"
#2140
b1111 &
1"
#2160
0"
#2180
b10000 &
1"
#2200
0"
#2220
b10001 &
1"
#2240
0"
#2260
b0 &
1"
#2280
0"
#2300
b1 &
1"
#2320
0"
#2340
b10 &
1"
#2360
0"
#2380
b11 &
1"
#2400
0"
#2420
b100 &
1"
#2440
0"
#2460
b101 &
1"
#2480
0"
#2500
b110 &
1"
b1111 !
#2520
0"
#2540
b111 &
1"
#2560
0"
#2580
b1000 &
1"
#2600
0"
#2620
b1001 &
1"
#2640
0"
#2660
b1010 &
1"
#2680
0"
#2700
b1011 &
1"
#2720
0"
#2740
b1100 &
1"
#2760
0"
#2780
b1101 &
1"
#2800
0"
#2820
b1110 &
1"
#2840
0"
#2860
b1111 &
1"
#2880
0"
#2900
b10000 &
1"
#2920
0"
#2940
b10001 &
1"
#2960
0"
#2980
b0 &
1"
#3000
0"
#3020
b1 &
1"
#3040
0"
#3060
b10 &
1"
#3080
0"
#3100
b11 &
1"
#3120
0"
#3140
b100 &
1"
#3160
0"
#3180
b101 &
1"
#3200
0"
#3220
b110 &
1"
#3240
0"
#3260
b111 &
1"
#3280
0"
#3300
b1000 &
1"
